balance_engine-0.0.2.dist-info/METADATA
balance_engine-0.0.2.dist-info/WHEEL
engine/__init__.py
engine/engine.pyd
balance_engine-0.0.2.dist-info/RECORD
