Metadata-Version: 2.4
Name: balance_engine
Version: 0.0.2
Classifier: Programming Language :: Rust
Classifier: Programming Language :: Python :: Implementation :: CPython
Classifier: Programming Language :: Python :: Implementation :: PyPy
Classifier: Topic :: Scientific/Engineering :: Mathematics
Classifier: Topic :: Scientific/Engineering :: Information Analysis
Classifier: Intended Audience :: Science/Research
Classifier: Intended Audience :: Manufacturing
Requires-Dist: matplotlib>=3.10.1
Requires-Dist: pulp>=3.1.1
Requires-Dist: scipy>=1.15.2
Requires-Dist: tabulate>=0.9.0
Requires-Dist: pytest ; extra == 'tests'
Provides-Extra: tests
Summary: Production planning and optimization engine using linear programming to balance supply with demand while minimizing costs and respecting resource constraints
Keywords: optimization,production-planning,linear-programming,supply-chain,inventory-management
Author: Fernando Bryan Reza Campos <fer.rezac@outlook.com>, Perla Edith Lugo Hernández <edithlugo@gmail.com>, Kevin Alexis Martínez Sánchez <xdkevinalexisxd120@gmail.com>, Fernando Ramírez López <frl23112001@gmail.com>
Author-email: Fernando Bryan Reza Campos <fer.rezac@outlook.com>, Perla Edith Lugo Hernández <edithlugo@gmail.com>, Kevin Alexis Martínez Sánchez <xdkevinalexisxd120@gmail.com>, Fernando Ramírez López <frl23112001@gmail.com>
License: MIT
Requires-Python: >=3.12
Project-URL: Repository, https://github.com/Yrrrrrf/balance_engine
Project-URL: Download, https://github.com/Yrrrrrf/balance_engine/releases
